{
  "project_info": {
    "project_number": "535083267122",
    "firebase_url": "https://android-dev-learning-default-rtdb.firebaseio.com",
    "project_id": "android-dev-learning",
    "storage_bucket": "android-dev-learning.appspot.com"
  },
  "client": [
    {
      "client_info": {
        "mobilesdk_app_id": "1:535083267122:android:4b9c2eb60dd0d74640f82b",
        "android_client_info": {
          "package_name": "com.sayempro.firebase"
        }
      },
      "oauth_client": [],
      "api_key": [
        {
          "current_key": "AIzaSyDvC_reg2XYABpLwzuXqIAOtVit91aFvMI"
        }
      ],
      "services": {
        "appinvite_service": {
          "other_platform_oauth_client": []
        }
      }
    }
  ],
  "configuration_version": "1"
}